{
    "swagger": "2.0",
    "info": {
        "description": "This is a simple API to manage transactions",
        "title": "Transactions API",
        "termsOfService": "https://developers.mercadolibre.com.ar/es_ar/terminos-y-condiciones",
        "contact": {
            "name": "Henrique Okuti",
            "url": "https://github.com/hokuti_meli/bootcamp-henriqueokuti"
        },
        "license": {
            "name": "Apache 2.0",
            "url": "http://www.apache.org/licenses/LICENSE-2.0.html"
        },
        "version": "1.0"
    },
    "host": "localhost:8080",
    "paths": {}
}